Tavin/__init__.py
Tavin-1.1.8.dist-info/LICENSE.txt
Tavin-1.1.8.dist-info/METADATA
Tavin-1.1.8.dist-info/WHEEL
Tavin-1.1.8.dist-info/top_level.txt
Tavin-1.1.8.dist-info/RECORD
