Metadata-Version: 2.1
Name: Tavin
Version: 1.1.8
Summary: A concise application framework.
Home-page: https://github.com/lemonorangeapple/Tavin
Author: lemonorangeapple
Author-email: jcj1947725596@hotmail.com
License: MIT
Keywords: web framework
Platform: UNKNOWN
Requires-Python: >=3
Requires-Dist: flask
Requires-Dist: pywebview
